aas_core_codegen/__init__.py
aas_core_codegen/__main__.py
aas_core_codegen/common.py
aas_core_codegen/main.py
aas_core_codegen/naming.py
aas_core_codegen/py.typed
aas_core_codegen/run.py
aas_core_codegen/specific_implementations.py
aas_core_codegen/stringify.py
aas_core_codegen/cpp/__init__.py
aas_core_codegen/cpp/common.py
aas_core_codegen/cpp/description.py
aas_core_codegen/cpp/main.py
aas_core_codegen/cpp/naming.py
aas_core_codegen/cpp/optionaling.py
aas_core_codegen/cpp/transpilation.py
aas_core_codegen/cpp/unrolling.py
aas_core_codegen/cpp/yielding.py
aas_core_codegen/cpp/aas_common/__init__.py
aas_core_codegen/cpp/aas_common/_generate.py
aas_core_codegen/cpp/constants/__init__.py
aas_core_codegen/cpp/constants/_generate.py
aas_core_codegen/cpp/enhancing/__init__.py
aas_core_codegen/cpp/enhancing/_generate.py
aas_core_codegen/cpp/iteration/__init__.py
aas_core_codegen/cpp/iteration/_generate.py
aas_core_codegen/cpp/jsonization/__init__.py
aas_core_codegen/cpp/jsonization/_generate.py
aas_core_codegen/cpp/pattern/__init__.py
aas_core_codegen/cpp/pattern/_generate.py
aas_core_codegen/cpp/revm/__init__.py
aas_core_codegen/cpp/revm/_generate.py
aas_core_codegen/cpp/stringification/__init__.py
aas_core_codegen/cpp/stringification/_generate.py
aas_core_codegen/cpp/structure/__init__.py
aas_core_codegen/cpp/structure/_generate.py
aas_core_codegen/cpp/verification/__init__.py
aas_core_codegen/cpp/verification/_generate.py
aas_core_codegen/cpp/visitation/__init__.py
aas_core_codegen/cpp/visitation/_generate.py
aas_core_codegen/cpp/wstringification/__init__.py
aas_core_codegen/cpp/wstringification/_generate.py
aas_core_codegen/cpp/xmlization/__init__.py
aas_core_codegen/cpp/xmlization/_generate.py
aas_core_codegen/csharp/__init__.py
aas_core_codegen/csharp/common.py
aas_core_codegen/csharp/description.py
aas_core_codegen/csharp/main.py
aas_core_codegen/csharp/naming.py
aas_core_codegen/csharp/transpilation.py
aas_core_codegen/csharp/unrolling.py
aas_core_codegen-0.0.16.dist-info/licenses/AUTHORS
aas_core_codegen-0.0.16.dist-info/licenses/LICENSE
aas_core_codegen-0.0.16.dist-info/METADATA
aas_core_codegen-0.0.16.dist-info/WHEEL
aas_core_codegen-0.0.16.dist-info/entry_points.txt
aas_core_codegen-0.0.16.dist-info/top_level.txt
aas_core_codegen-0.0.16.dist-info/RECORD
