Metadata-Version: 2.4
Name: aas-core-codegen
Version: 0.0.16
Summary: Generate implementations and schemas based on an AAS meta-model.
Author-email: Marko Ristin <marko@ristin.ch>, Nico Braunisch <nico.braunisch@tu-dresden.de>
License: MIT
Project-URL: Homepage, https://github.com/aas-core-works/aas-core-codegen
Keywords: asset administration shell,code generation,industry 4.0,industrie 4.0,i4.0
Classifier: Development Status :: 5 - Production/Stable
Classifier: License :: OSI Approved :: MIT License
Classifier: Programming Language :: Python :: 3.9
Classifier: Programming Language :: Python :: 3.10
Classifier: Programming Language :: Python :: 3.11
Classifier: Programming Language :: Python :: 3.12
Requires-Python: >=3.9
License-File: LICENSE
License-File: AUTHORS
Requires-Dist: asttokens<3,>=2.0.8
Requires-Dist: icontract<3,>=2.5.2
Requires-Dist: sortedcontainers<3,>=2.4.0
Requires-Dist: docutils==0.22.3
Requires-Dist: more-itertools<9,>=8
Requires-Dist: greenery==4.1.0
Dynamic: license-file
